unmagic/__init__.py
unmagic/_api.py
unmagic/autouse.py
unmagic/fence.py
unmagic/fixtures.py
unmagic/scope.py
pytest_unmagic-1.0.1.dist-info/entry_points.txt
pytest_unmagic-1.0.1.dist-info/licenses/LICENSE
pytest_unmagic-1.0.1.dist-info/WHEEL
pytest_unmagic-1.0.1.dist-info/METADATA
pytest_unmagic-1.0.1.dist-info/RECORD
