Metadata-Version: 2.4
Name: pytest-unmagic
Version: 1.0.1
Summary: Pytest fixtures with conventional import semantics
Author-email: Daniel Miller <millerdev@gmail.com>
Requires-Python: >= 3.9
Classifier: Development Status :: 5 - Production/Stable
Classifier: Intended Audience :: Developers
Classifier: License :: OSI Approved :: BSD License
Classifier: Programming Language :: Python :: 3
Classifier: Programming Language :: Python :: 3.9
Classifier: Programming Language :: Python :: 3.10
Classifier: Programming Language :: Python :: 3.11
Classifier: Programming Language :: Python :: 3.12
Classifier: Programming Language :: Python :: 3.13
Classifier: Topic :: Software Development :: Libraries
Classifier: Topic :: Software Development :: Testing
License-File: LICENSE
Requires-Dist: pytest
Project-URL: Home, https://github.com/dimagi/pytest-unmagic
